datapackage_pipelines/VERSION
datapackage_pipelines/__init__.py
datapackage_pipelines/app.py
datapackage_pipelines/cli.py
datapackage_pipelines/celery_tasks/__init__.py
datapackage_pipelines/celery_tasks/celery_app.py
datapackage_pipelines/celery_tasks/celery_common.py
datapackage_pipelines/celery_tasks/celery_tasks.py
datapackage_pipelines/celery_tasks/dependency_manager.py
datapackage_pipelines/generators/__init__.py
datapackage_pipelines/generators/generator_base.py
datapackage_pipelines/generators/schedules.py
datapackage_pipelines/generators/utilities.py
datapackage_pipelines/lib/__init__.py
datapackage_pipelines/lib/add_computed_field.py
datapackage_pipelines/lib/add_metadata.py
datapackage_pipelines/lib/add_resource.py
datapackage_pipelines/lib/cache_loader.py
datapackage_pipelines/lib/concatenate.py
datapackage_pipelines/lib/deduplicate.py
datapackage_pipelines/lib/delete_fields.py
datapackage_pipelines/lib/dump_to_path.py
datapackage_pipelines/lib/dump_to_sql.py
datapackage_pipelines/lib/dump_to_zip.py
datapackage_pipelines/lib/duplicate.py
datapackage_pipelines/lib/filter.py
datapackage_pipelines/lib/find_replace.py
datapackage_pipelines/lib/flow.py
datapackage_pipelines/lib/join.py
datapackage_pipelines/lib/load.py
datapackage_pipelines/lib/load_metadata.py
datapackage_pipelines/lib/load_resource.py
datapackage_pipelines/lib/printer.py
datapackage_pipelines/lib/set_types.py
datapackage_pipelines/lib/sort.py
datapackage_pipelines/lib/stream_remote_resources.py
datapackage_pipelines/lib/unpivot.py
datapackage_pipelines/lib/update_package.py
datapackage_pipelines/lib/update_resource.py
datapackage_pipelines/lib/dump/__init__.py
datapackage_pipelines/lib/dump/dumper_base.py
datapackage_pipelines/lib/dump/file_formats.py
datapackage_pipelines/lib/dump/to_path.py
datapackage_pipelines/lib/dump/to_sql.py
datapackage_pipelines/lib/dump/to_zip.py
datapackage_pipelines/lib/internal/__init__.py
datapackage_pipelines/lib/internal/sink.py
datapackage_pipelines-2.2.11.dist-info/LICENSE.md
datapackage_pipelines-2.2.11.dist-info/METADATA
datapackage_pipelines-2.2.11.dist-info/WHEEL
datapackage_pipelines-2.2.11.dist-info/entry_points.txt
datapackage_pipelines-2.2.11.dist-info/top_level.txt
datapackage_pipelines-2.2.11.dist-info/RECORD
