Metadata-Version: 2.1
Name: datapackage-pipelines
Version: 2.2.11
Summary: {{ DESCRIPTION }}
Home-page: https://github.com/frictionlessdata/datapackage-pipelines
Author: Open Knowledge Foundation
Author-email: info@okfn.org
License: MIT
Keywords: data
Platform: UNKNOWN
Classifier: Development Status :: 4 - Beta
Classifier: Intended Audience :: Developers
Classifier: License :: OSI Approved :: MIT License
Classifier: Operating System :: OS Independent
Classifier: Programming Language :: Python :: 3.6
Classifier: Topic :: Software Development :: Libraries :: Python Modules
License-File: LICENSE.md
Requires-Dist: celery (<5)
Requires-Dist: requests
Requires-Dist: datapackage (>=1.14.0)
Requires-Dist: tableschema (>=1.2.5)
Requires-Dist: tableschema-sql (>=0.10.4)
Requires-Dist: pyyaml
Requires-Dist: ujson
Requires-Dist: mistune (<2)
Requires-Dist: markupsafe (==2.0.1)
Requires-Dist: redis (<4,>=3)
Requires-Dist: click (<8.0)
Requires-Dist: awesome-slugify
Requires-Dist: flask (<2.0.0)
Requires-Dist: flask-cors
Requires-Dist: flask-jsonpify
Requires-Dist: flask-basicauth
Requires-Dist: cachetools
Requires-Dist: tabulator (>=1.50.0)
Requires-Dist: globster (>=0.1.0)
Requires-Dist: dataflows (>=0.2.11)
Requires-Dist: python-dateutil (<2.8.1)
Requires-Dist: werkzeug (<1.0)
Provides-Extra: develop
Requires-Dist: pylama ; extra == 'develop'
Requires-Dist: tox ; extra == 'develop'
Requires-Dist: sqlalchemy ; extra == 'develop'
Provides-Extra: speedup
Requires-Dist: dataflows[speedup] ; extra == 'speedup'
